high_pass_filters/__init__.py
high_pass_filters/fprewitt.py
high_pass_filters/fsobel.py
high_pass_filters/image.py
high_pass_filters-0.0.1.dist-info/METADATA
high_pass_filters-0.0.1.dist-info/WHEEL
high_pass_filters-0.0.1.dist-info/top_level.txt
high_pass_filters-0.0.1.dist-info/RECORD
