Metadata-Version: 2.1
Name: high-pass-filters
Version: 0.0.1
Summary: high-pass filter package using Sobel and Prewitt
Home-page: https://github.com/Leo22080/hpf-package-sobel-prewitt.git
Author: Leonardo
Author-email: leonardo.costa.sousa84@aluno.ifce.edu.br
License: UNKNOWN
Platform: UNKNOWN
Requires-Python: >=3.7
Requires-Dist: numpy
Requires-Dist: matplotlib
